gmxpy/__init__.py
gmxpy/config.py
gmxpy/main.py
gmxpy/analysis/__init__.py
gmxpy/analysis/functional.py
gmxpy/editconf/__init__.py
gmxpy/grompp/__init__.py
gmxpy/grompp/functional.py
gmxpy/solvate/__init__.py
"gmxpy/utils/__init__,py"
gmxpy/utils/functional.py
gmxpy-0.0.5.dist-info/METADATA
gmxpy-0.0.5.dist-info/WHEEL
gmxpy-0.0.5.dist-info/licenses/LICENSE
gmxpy-0.0.5.dist-info/RECORD
