Metadata-Version: 2.3
Name: gmxpy
Version: 0.0.5
Summary: Wrapping GROMACS by Python for me
Project-URL: Homepage, https://github.com/Goosang-Yu/gmxpy
Project-URL: Repository, https://github.com/Goosang-Yu/gmxpy
Project-URL: Source, https://github.com/Goosang-Yu/gmxpy
Project-URL: Tracker, https://github.com/Goosang-Yu/gmxpy/issues
Author-email: Goosang Yu <gsyu93@gmail.com>
License-Expression: MIT
License-File: LICENSE
Keywords: analysis,gromacs,molecular dynamics,simulation
Classifier: Intended Audience :: Developers
Classifier: Intended Audience :: Science/Research
Classifier: License :: OSI Approved :: MIT License
Classifier: Operating System :: Unix
Classifier: Programming Language :: Python
Classifier: Programming Language :: Python :: 3 :: Only
Classifier: Programming Language :: Python :: 3.7
Classifier: Programming Language :: Python :: 3.8
Classifier: Programming Language :: Python :: 3.9
Classifier: Programming Language :: Python :: 3.10
Classifier: Programming Language :: Python :: 3.11
Classifier: Topic :: Software Development
Classifier: Topic :: Software Development :: Libraries
Classifier: Topic :: Software Development :: Libraries :: Application Frameworks
Classifier: Topic :: Software Development :: Libraries :: Python Modules
Classifier: Typing :: Typed
Requires-Python: >=3.7
Requires-Dist: matplotlib
Requires-Dist: pandas
